spliit_client/__init__.py
spliit_client/__main__.py
spliit_client/client.py
spliit_client-0.1.0.dist-info/licenses/LICENSE
tests/__init__.py
tests/test_client.py
spliit_client-0.1.0.dist-info/METADATA
spliit_client-0.1.0.dist-info/WHEEL
spliit_client-0.1.0.dist-info/entry_points.txt
spliit_client-0.1.0.dist-info/top_level.txt
spliit_client-0.1.0.dist-info/RECORD
