Metadata-Version: 2.4
Name: spliit_client
Version: 0.1.0
Summary: A Python client for the Spliit API (group expense sharing)
Home-page: https://github.com/abg0148/spliit_client
Author: Abhinav
Author-email: Abhinav <gptabhinav0148@gmail.com>
License: MIT
Project-URL: Homepage, https://github.com/abg0148/spliit_client
Project-URL: Repository, https://github.com/abg0148/spliit_client
Project-URL: Documentation, https://github.com/abg0148/spliit_client#readme
Project-URL: Bug Reports, https://github.com/abg0148/spliit_client/issues
Keywords: spliit,expense,sharing,api,client,group,expenses
Classifier: Development Status :: 4 - Beta
Classifier: Intended Audience :: Developers
Classifier: License :: OSI Approved :: MIT License
Classifier: Operating System :: OS Independent
Classifier: Programming Language :: Python :: 3
Classifier: Programming Language :: Python :: 3.7
Classifier: Programming Language :: Python :: 3.8
Classifier: Programming Language :: Python :: 3.9
Classifier: Programming Language :: Python :: 3.10
Classifier: Programming Language :: Python :: 3.11
Classifier: Programming Language :: Python :: 3.12
Classifier: Topic :: Software Development :: Libraries :: Python Modules
Classifier: Topic :: Office/Business :: Financial :: Accounting
Requires-Python: >=3.7
License-File: LICENSE
Requires-Dist: requests>=2.25.0
Provides-Extra: dev
Requires-Dist: pytest>=6.0; extra == "dev"
Requires-Dist: pytest-cov>=2.0; extra == "dev"
Requires-Dist: black>=21.0; extra == "dev"
Requires-Dist: flake8>=3.8; extra == "dev"
Requires-Dist: mypy>=0.800; extra == "dev"
Requires-Dist: twine>=3.0; extra == "dev"
Requires-Dist: build>=0.7; extra == "dev"
Dynamic: author
Dynamic: home-page
Dynamic: license-file
Dynamic: requires-python
